textual_query_sandbox/__init__.py
textual_query_sandbox/__main__.py
textual_query_sandbox/sandbox.py
textual_query_sandbox-0.6.0.dist-info/METADATA
textual_query_sandbox-0.6.0.dist-info/WHEEL
textual_query_sandbox-0.6.0.dist-info/entry_points.txt
textual_query_sandbox-0.6.0.dist-info/top_level.txt
textual_query_sandbox-0.6.0.dist-info/RECORD
