Metadata-Version: 2.1
Name: textual-query-sandbox
Version: 0.6.0
Summary: A sandbox for practicing Textual queries
Home-page: https://github.com/davep/textual-query-sandbox
Author: Dave Pearson
Author-email: davep@davep.org
Maintainer: Dave Pearson
Maintainer-email: davep@davep.org
License: License :: OSI Approved :: GNU General Public License v3 or later (GPLv3+)
Project-URL: Documentation, https://github.com/davep/textual-query-sandbox/blob/main/README.md
Project-URL: Source, https://github.com/davep/textual-query-sandbox
Project-URL: Issues, https://github.com/davep/textual-query-sandbox/issues
Project-URL: Discussions, https://github.com/davep/textual-query-sandbox/discussions
Keywords: terminal
Classifier: License :: OSI Approved :: GNU General Public License v3 or later (GPLv3+)
Classifier: Environment :: Console
Classifier: Development Status :: 3 - Alpha
Classifier: Intended Audience :: Developers
Classifier: Operating System :: OS Independent
Classifier: Programming Language :: Python :: 3.8
Classifier: Programming Language :: Python :: 3.9
Classifier: Programming Language :: Python :: 3.10
Classifier: Programming Language :: Python :: 3.11
Classifier: Topic :: Terminals
Requires-Python: >=3.8
Requires-Dist: textual >=0.56.3
